[
  {
    "id": "dlf-kultur-heute:5d73745b-2696-5aa4-98c0-ecc2ddec88c4",
    "source": "dlf-kultur-heute",
    "sourceTitle": "Kultur heute – Deutschlandfunk",
    "type": "rss",
    "title": "Kulturmeldungen 21.07.2026",
    "summary": "Fischer, Karin www.deutschlandfunk.de, Kultur heute",
    "date": "2026-07-21T15:56:15.000Z",
    "url": "https://www.deutschlandfunk.de/kulturmeldungen-21-07-102.html",
    "image": "https://bilder.deutschlandfunk.de/FI/LE/_a/2b/FILE_a2b492ca7166500c6ef32d7a9e8618d7/kultur-heute-16x9-jpg-100-1920x1920.jpg",
    "audio": "https://podcast-mp3.dradio.de/podcast/2026/07/21/kulturmeldungen_21072026_dlf_20260721_1756_1b84a88e.mp3?refId=kultur-heute-104",
    "duration": "3 Min",
    "tags": [
      "kultur",
      "theater",
      "kunst",
      "film",
      "kulturpolitik",
      "deutschlandfunk"
    ],
    "category": [
      "Kultur",
      "Gesellschaft"
    ],
    "language": "de"
  },
  {
    "id": "dlf-kultur-heute:8d3b0d09-6b0e-50b0-9c47-96b136698d6a",
    "source": "dlf-kultur-heute",
    "sourceTitle": "Kultur heute – Deutschlandfunk",
    "type": "rss",
    "title": "\"Tage aus Glas\" - Theatraler Stadtrundgang beim Asphalt Festival Düsseldorf",
    "summary": "Marcus, Dorothea www.deutschlandfunk.de, Kultur heute",
    "date": "2026-07-21T15:50:50.000Z",
    "url": "https://www.deutschlandfunk.de/tage-aus-glas-theatraler-stadtrundgang-beim-asphalt-festival-duesseldorf-100.html",
    "image": "https://bilder.deutschlandfunk.de/FI/LE/_a/2b/FILE_a2b492ca7166500c6ef32d7a9e8618d7/kultur-heute-16x9-jpg-100-1920x1920.jpg",
    "audio": "https://podcast-mp3.dradio.de/podcast/2026/07/21/tage_aus_glas_theatraler_stadtrundgang_beim_asphalt_festival_dlf_20260721_1750_af835456.mp3?refId=kultur-heute-104",
    "duration": "6 Min",
    "tags": [
      "kultur",
      "theater",
      "kunst",
      "film",
      "kulturpolitik",
      "deutschlandfunk"
    ],
    "category": [
      "Kultur",
      "Gesellschaft"
    ],
    "language": "de"
  },
  {
    "id": "dlf-kultur-heute:4bb5357e-3560-5c0c-9c38-5cfb5277e4c7",
    "source": "dlf-kultur-heute",
    "sourceTitle": "Kultur heute – Deutschlandfunk",
    "type": "rss",
    "title": "Gemeinsam Literatur erleben - das Literaturfestival \"kindly invited\" in Köln",
    "summary": "Seidel, Änne; Reiner, Svenja www.deutschlandfunk.de, Kultur heute",
    "date": "2026-07-21T15:43:28.000Z",
    "url": "https://www.deutschlandfunk.de/gemeinsam-literatur-erleben-das-literaturfestival-kindly-invited-in-koeln-100.html",
    "image": "https://bilder.deutschlandfunk.de/FI/LE/_a/2b/FILE_a2b492ca7166500c6ef32d7a9e8618d7/kultur-heute-16x9-jpg-100-1920x1920.jpg",
    "audio": "https://podcast-mp3.dradio.de/podcast/2026/07/21/gemeinsam_literatur_erleben_das_literaturfestival_kindly_dlf_20260721_1743_3b824731.mp3?refId=kultur-heute-104",
    "duration": "7 Min",
    "tags": [
      "kultur",
      "theater",
      "kunst",
      "film",
      "kulturpolitik",
      "deutschlandfunk"
    ],
    "category": [
      "Kultur",
      "Gesellschaft"
    ],
    "language": "de"
  },
  {
    "id": "dlf-kultur-heute:9e13d361-7fbf-5629-9b70-1d6cffc699bc",
    "source": "dlf-kultur-heute",
    "sourceTitle": "Kultur heute – Deutschlandfunk",
    "type": "rss",
    "title": "Nightborne - Filmwissenschaftler Marcus Stiglegger über KI-generierten Kurzfilm",
    "summary": "Seidel, Änne www.deutschlandfunk.de, Kultur heute",
    "date": "2026-07-21T15:35:20.000Z",
    "url": "https://www.deutschlandfunk.de/nightborne-filmwissenschaftler-marcus-stiglegger-ueber-ki-generierten-kurzfilm-100.html",
    "image": "https://bilder.deutschlandfunk.de/FI/LE/_a/2b/FILE_a2b492ca7166500c6ef32d7a9e8618d7/kultur-heute-16x9-jpg-100-1920x1920.jpg",
    "audio": "https://podcast-mp3.dradio.de/podcast/2026/07/21/nightborne_filmwissenschaftler_marcus_stiglegger_ueber_ki_dlf_20260721_1735_4d80e4fa.mp3?refId=kultur-heute-104",
    "duration": "9 Min",
    "tags": [
      "kultur",
      "theater",
      "kunst",
      "film",
      "kulturpolitik",
      "deutschlandfunk"
    ],
    "category": [
      "Kultur",
      "Gesellschaft"
    ],
    "language": "de"
  },
  {
    "id": "dlf-kultur-heute:43b55b1b-3eba-5555-a7e6-2d9d701d7ff6",
    "source": "dlf-kultur-heute",
    "sourceTitle": "Kultur heute – Deutschlandfunk",
    "type": "rss",
    "title": "Kulturmeldungen 20.07.2026",
    "summary": "Strecker, Nicole www.deutschlandfunk.de, Kultur heute",
    "date": "2026-07-20T15:56:06.000Z",
    "url": "https://www.deutschlandfunk.de/kulturmeldungen-20-07-102.html",
    "image": "https://bilder.deutschlandfunk.de/FI/LE/_a/2b/FILE_a2b492ca7166500c6ef32d7a9e8618d7/kultur-heute-16x9-jpg-100-1920x1920.jpg",
    "audio": "https://podcast-mp3.dradio.de/podcast/2026/07/20/kulturmeldungen_20072026_dlf_20260720_1756_1257c8cc.mp3?refId=kultur-heute-104",
    "duration": "3 Min",
    "tags": [
      "kultur",
      "theater",
      "kunst",
      "film",
      "kulturpolitik",
      "deutschlandfunk"
    ],
    "category": [
      "Kultur",
      "Gesellschaft"
    ],
    "language": "de"
  },
  {
    "id": "dlf-kultur-heute:0f9723c0-af22-5b61-baaa-9dfc0f4d4408",
    "source": "dlf-kultur-heute",
    "sourceTitle": "Kultur heute – Deutschlandfunk",
    "type": "rss",
    "title": "\"Vergiss es?!\" - Kampagne der Gedenkstätten in Sachsen-Anhalt",
    "summary": "Ottersbach, Niklas www.deutschlandfunk.de, Kultur heute",
    "date": "2026-07-20T15:51:05.000Z",
    "url": "https://www.deutschlandfunk.de/vergiss-es-kampagne-der-gedenkstaetten-in-sachsen-anhalt-100.html",
    "image": "https://bilder.deutschlandfunk.de/FI/LE/_a/2b/FILE_a2b492ca7166500c6ef32d7a9e8618d7/kultur-heute-16x9-jpg-100-1920x1920.jpg",
    "audio": "https://podcast-mp3.dradio.de/podcast/2026/07/20/vergiss_es_kampagne_der_gedenkstaetten_in_sachsen_anhalt_dlf_20260720_1751_a956527c.mp3?refId=kultur-heute-104",
    "duration": "5 Min",
    "tags": [
      "kultur",
      "theater",
      "kunst",
      "film",
      "kulturpolitik",
      "deutschlandfunk"
    ],
    "category": [
      "Kultur",
      "Gesellschaft"
    ],
    "language": "de"
  },
  {
    "id": "dlf-kultur-heute:391ba1ba-e338-5452-a5e3-9256b0907fdc",
    "source": "dlf-kultur-heute",
    "sourceTitle": "Kultur heute – Deutschlandfunk",
    "type": "rss",
    "title": "Soundwalk Collective mit Patti Smith im LUMA Arles",
    "summary": "Broecking, Maxi www.deutschlandfunk.de, Kultur heute",
    "date": "2026-07-20T15:45:45.000Z",
    "url": "https://www.deutschlandfunk.de/soundwalk-collective-mit-patti-smith-im-luma-arles-100.html",
    "image": "https://bilder.deutschlandfunk.de/FI/LE/_a/2b/FILE_a2b492ca7166500c6ef32d7a9e8618d7/kultur-heute-16x9-jpg-100-1920x1920.jpg",
    "audio": "https://podcast-mp3.dradio.de/podcast/2026/07/20/soundwalk_collective_mit_patti_smith_im_luma_arles_dlf_20260720_1745_83553a2b.mp3?refId=kultur-heute-104",
    "duration": "5 Min",
    "tags": [
      "kultur",
      "theater",
      "kunst",
      "film",
      "kulturpolitik",
      "deutschlandfunk"
    ],
    "category": [
      "Kultur",
      "Gesellschaft"
    ],
    "language": "de"
  },
  {
    "id": "dlf-kultur-heute:8cca7b04-4e6c-5b4d-b6ae-ac8a585a081e",
    "source": "dlf-kultur-heute",
    "sourceTitle": "Kultur heute – Deutschlandfunk",
    "type": "rss",
    "title": "Berliner Fördergeldaffäre: Untersuchungsausschuss legt Abschlussbericht vor",
    "summary": "van Laak, Claudia www.deutschlandfunk.de, Kultur heute",
    "date": "2026-07-20T15:40:55.000Z",
    "url": "https://www.deutschlandfunk.de/berliner-foerdergeldaffaere-untersuchungsausschuss-legt-abschlussbericht-vor-100.html",
    "image": "https://bilder.deutschlandfunk.de/FI/LE/_a/2b/FILE_a2b492ca7166500c6ef32d7a9e8618d7/kultur-heute-16x9-jpg-100-1920x1920.jpg",
    "audio": "https://podcast-mp3.dradio.de/podcast/2026/07/20/berliner_foerdergeldaffaere_untersuchungsausschuss_legt_dlf_20260720_1740_ee542bb9.mp3?refId=kultur-heute-104",
    "duration": "5 Min",
    "tags": [
      "kultur",
      "theater",
      "kunst",
      "film",
      "kulturpolitik",
      "deutschlandfunk"
    ],
    "category": [
      "Kultur",
      "Gesellschaft"
    ],
    "language": "de"
  },
  {
    "id": "dlf-kultur-heute:d05fbe19-3c95-58ce-8fab-dd0232ef998c",
    "source": "dlf-kultur-heute",
    "sourceTitle": "Kultur heute – Deutschlandfunk",
    "type": "rss",
    "title": "Weltmuseum ohne Kern - Philipp Oswalt zu fünf Jahren Humboldtforum",
    "summary": "Köhler, Michael www.deutschlandfunk.de, Kultur heute",
    "date": "2026-07-20T15:35:13.000Z",
    "url": "https://www.deutschlandfunk.de/weltmuseum-ohne-kern-philipp-oswalt-zu-fuenf-jahren-humboldtforum-100.html",
    "image": "https://bilder.deutschlandfunk.de/FI/LE/_a/2b/FILE_a2b492ca7166500c6ef32d7a9e8618d7/kultur-heute-16x9-jpg-100-1920x1920.jpg",
    "audio": "https://podcast-mp3.dradio.de/podcast/2026/07/20/weltmuseum_ohne_kern_philipp_oswalt_zu_fuenf_jahren_dlf_20260720_1735_de532886.mp3?refId=kultur-heute-104",
    "duration": "6 Min",
    "tags": [
      "kultur",
      "theater",
      "kunst",
      "film",
      "kulturpolitik",
      "deutschlandfunk"
    ],
    "category": [
      "Kultur",
      "Gesellschaft"
    ],
    "language": "de"
  },
  {
    "id": "dlf-kultur-heute:https-podcast-mp3-dradio-de-podcast-2026-07-19-kulturmeldungen-19072026-dlf-20260719-1756-2d2d4994-mp3-refid-kultur-heute-104",
    "source": "dlf-kultur-heute",
    "sourceTitle": "Kultur heute – Deutschlandfunk",
    "type": "rss",
    "title": "Kulturmeldungen 19.07.2026",
    "summary": "Biesler, Jörg www.deutschlandfunk.de, Kultur heute",
    "date": "2026-07-19T15:56:00.000Z",
    "url": "https://www.deutschlandfunk.de/kulturmeldungen-19-07-102.html",
    "image": "https://bilder.deutschlandfunk.de/FI/LE/_a/2b/FILE_a2b492ca7166500c6ef32d7a9e8618d7/kultur-heute-16x9-jpg-100-1920x1920.jpg",
    "audio": "https://podcast-mp3.dradio.de/podcast/2026/07/19/kulturmeldungen_19072026_dlf_20260719_1756_2d2d4994.mp3?refId=kultur-heute-104",
    "duration": "4 Min",
    "tags": [
      "kultur",
      "theater",
      "kunst",
      "film",
      "kulturpolitik",
      "deutschlandfunk"
    ],
    "category": [
      "Kultur",
      "Gesellschaft"
    ],
    "language": "de"
  }
]
